click_shell-stubs/METADATA.toml
click_shell-stubs/__init__.pyi
click_shell-stubs/_cmd.pyi
click_shell-stubs/_compat.pyi
click_shell-stubs/core.pyi
click_shell-stubs/decorators.pyi
click_shell-stubs/py.typed
types_click_shell-2.1.0.20250821.dist-info/licenses/LICENSE
types_click_shell-2.1.0.20250821.dist-info/METADATA
types_click_shell-2.1.0.20250821.dist-info/WHEEL
types_click_shell-2.1.0.20250821.dist-info/top_level.txt
types_click_shell-2.1.0.20250821.dist-info/RECORD
